moPepGen/SeqFeature.py
moPepGen/__init__.py
moPepGen/constant.py
moPepGen/err.py
moPepGen/fake.py
moPepGen/index.py
moPepGen/params.py
moPepGen/version.py
moPepGen/aa/AminoAcidSeqDict.py
moPepGen/aa/AminoAcidSeqRecord.py
moPepGen/aa/PeptidePoolSplitter.py
moPepGen/aa/PeptidePoolSummarizer.py
moPepGen/aa/VariantPeptideIdentifier.py
moPepGen/aa/VariantPeptideLabel.py
moPepGen/aa/VariantPeptidePool.py
moPepGen/aa/__init__.py
moPepGen/aa/expasy_rules.py
moPepGen/circ/CircRNA.py
moPepGen/circ/__init__.py
moPepGen/circ/io.py
moPepGen/cli/__init__.py
moPepGen/cli/__main__.py
moPepGen/cli/call_alt_translation.py
moPepGen/cli/call_novel_orf.py
moPepGen/cli/call_variant_peptide.py
moPepGen/cli/common.py
moPepGen/cli/decoy_fasta.py
moPepGen/cli/encode_fasta.py
moPepGen/cli/filter_fasta.py
moPepGen/cli/generate_index.py
moPepGen/cli/index_gvf.py
moPepGen/cli/merge_fasta.py
moPepGen/cli/parse_arriba.py
moPepGen/cli/parse_circexplorer.py
moPepGen/cli/parse_fusion_catcher.py
moPepGen/cli/parse_reditools.py
moPepGen/cli/parse_rmats.py
moPepGen/cli/parse_star_fusion.py
moPepGen/cli/parse_vep.py
moPepGen/cli/split_fasta.py
moPepGen/cli/summarize_fasta.py
moPepGen/cli/update_index.py
moPepGen/data/gencode_hs_exclusion_list.txt
moPepGen/dna/DNASeqDict.py
moPepGen/dna/DNASeqRecord.py
moPepGen/dna/__init__.py
moPepGen/gtf/GTFPointer.py
moPepGen/gtf/GTFRecord.py
moPepGen/gtf/GTFSeqFeature.py
moPepGen/gtf/GTFSourceInferrer.py
moPepGen/gtf/GeneAnnotationModel.py
moPepGen/gtf/GenomicAnnotation.py
moPepGen/gtf/GenomicAnnotationOnDisk.py
moPepGen/gtf/GtfIO.py
moPepGen/gtf/TranscriptAnnotationModel.py
moPepGen/gtf/__init__.py
moPepGen/parser/ArribaParser.py
moPepGen/parser/CIRCexplorerParser.py
moPepGen/parser/FusionCatcherParser.py
moPepGen/parser/REDItoolsParser.py
moPepGen/parser/STARFusionParser.py
moPepGen/parser/VEPParser.py
moPepGen/parser/__init__.py
moPepGen/parser/RMATSParser/A3SSRecord.py
moPepGen/parser/RMATSParser/A5SSRecord.py
moPepGen/parser/RMATSParser/MXERecord.py
mopepgen-1.4.6.dist-info/licenses/LICENSE.txt
mopepgen-1.4.6.dist-info/METADATA
mopepgen-1.4.6.dist-info/WHEEL
mopepgen-1.4.6.dist-info/entry_points.txt
mopepgen-1.4.6.dist-info/top_level.txt
mopepgen-1.4.6.dist-info/RECORD
