Metadata-Version: 2.4
Name: mopepgen
Version: 1.4.6
Summary: Multi-omic peptide generator
Home-page: https://github.com/uclahs-cds/package-moPepGen
Author: Chenghao Zhu, Yiyang Liu
Author-email: ChenghaoZhu@mednet.ucla.edu, yiyangliu@mednet.ucla.edu
Project-URL: Bug Tracker, https://github.com/uclahs-cds/package-moPepGen/issues
Classifier: Programming Language :: Python :: 3
Classifier: License :: OSI Approved :: GNU General Public License v2 (GPLv2)
Classifier: Operating System :: OS Independent
Requires-Python: >=3.7
License-File: LICENSE.txt
Requires-Dist: biopython<=1.83
Requires-Dist: psutil
Requires-Dist: pathos
Requires-Dist: six
Requires-Dist: matplotlib
Requires-Dist: regex
Dynamic: license-file
